django_auth_ldap3_ad/__init__.py
django_auth_ldap3_ad/ad_users.py
django_auth_ldap3_ad/auth.py
django_auth_ldap3_ad-1.6.33.dist-info/LICENSE
django_auth_ldap3_ad-1.6.33.dist-info/METADATA
django_auth_ldap3_ad-1.6.33.dist-info/WHEEL
django_auth_ldap3_ad-1.6.33.dist-info/top_level.txt
django_auth_ldap3_ad-1.6.33.dist-info/RECORD
