Metadata-Version: 2.1
Name: django-auth-ldap3-ad
Version: 1.6.33
Summary: very simple authentication module for python3 / django / LDAP or AD
Home-page: https://github.com/Lucterios2/django_auth_ldap3_ad
Author: Pierre-Olivier VERSCHOORE
Author-email: po.verschoore@sd-libre.fr
License: GPL V3
Platform: UNKNOWN
Classifier: Development Status :: 5 - Production/Stable
Classifier: Environment :: Web Environment
Classifier: Framework :: Django :: 1.11
Classifier: Intended Audience :: Developers
Classifier: Intended Audience :: End Users/Desktop
Classifier: License :: OSI Approved :: GNU General Public License v3 (GPLv3)
Classifier: Operating System :: OS Independent
Classifier: Programming Language :: Python
Requires-Dist: Django (>=1.11)
Requires-Dist: ldap3 (>=0.9.8)
Requires-Dist: six
